{
    "openapi": "3.1.0",
    "info": [],
    "paths": {
        "/seo-url": {
            "post": {
                "tags": [
                    "Sitemap & Routes",
                    "Endpoints supporting Criteria "
                ],
                "summary": "Fetch SEO routes",
                "description": "Perform a filtered search for seo urls.",
                "operationId": "readSeoUrl",
                "parameters": [
                    {
                        "name": "sw-include-search-info",
                        "in": "header",
                        "description": "Controls whether API search information is included in the response. Default is 1 (enabled), will be 0 (disabled) in the next major version.",
                        "required": false,
                        "schema": {
                            "type": "string",
                            "enum": [
                                "0",
                                "1"
                            ],
                            "default": "1"
                        }
                    }
                ],
                "requestBody": {
                    "required": false,
                    "content": {
                        "application/json": {
                            "schema": {
                                "allOf": [
                                    {
                                        "$ref": "#/components/schemas/Criteria"
                                    }
                                ]
                            }
                        }
                    }
                },
                "responses": {
                    "200": {
                        "$ref": "#/components/responses/SeoUrlListResponse"
                    },
                    "404": {
                        "$ref": "#/components/responses/404"
                    }
                },
                "security": [
                    {
                        "ApiKey": []
                    }
                ]
            },
            "get": {
                "tags": [
                    "Sitemap & Routes",
                    "Endpoints supporting Criteria "
                ],
                "summary": "Fetch SEO routes",
                "description": "Perform a filtered search for seo urls.",
                "operationId": "readSeoUrlGet",
                "parameters": [
                    {
                        "x-parameter-group": "criteria"
                    }
                ],
                "responses": {
                    "200": {
                        "$ref": "#/components/responses/SeoUrlListResponse"
                    },
                    "404": {
                        "$ref": "#/components/responses/404"
                    }
                },
                "security": [
                    {
                        "ApiKey": []
                    }
                ]
            }
        }
    }
}
